__init__.py
img_scrapper.py
img_scrapper-0.0.17.dist-info/LICENSE
img_scrapper-0.0.17.dist-info/METADATA
img_scrapper-0.0.17.dist-info/WHEEL
img_scrapper-0.0.17.dist-info/top_level.txt
img_scrapper-0.0.17.dist-info/RECORD
