Metadata-Version: 2.1
Name: img-scrapper
Version: 0.0.17
Summary: python package to scrap image from google image search
Home-page: https://github.com/vatshgaurav/img_scrapper
Author: Gaurav Vatsh
Author-email: vatshgaurav@gmail.com
Classifier: Programming Language :: Python :: 3.10
Classifier: License :: OSI Approved :: MIT License
Classifier: Operating System :: OS Independent
Requires-Python: >=3.6
License-File: LICENSE
Requires-Dist: beautifulsoup4 (==4.12.2)
Requires-Dist: bs4 (==0.0.1)
Requires-Dist: certifi (==2022.12.7)
Requires-Dist: lxml (==4.9.2)
Requires-Dist: requests (==2.28.2)
Requires-Dist: soupsieve (==2.4)
Requires-Dist: tomli (==2.0.1)
Requires-Dist: urllib3 (==1.26.15)
